fabrique_atelier/__init__.py
fabrique_atelier/actors.py
fabrique_atelier/config_generator.py
fabrique_atelier/constants.py
fabrique_atelier/dockerfile_generator.py
fabrique_atelier/message.py
fabrique_atelier/templates_generator.py
fabrique_atelier/buffered/__init__.py
fabrique_atelier/buffered/buffered_metrics.py
fabrique_atelier/data/default_template.yml
fabrique_atelier/dummy/__init__.py
fabrique_atelier/dummy/event_time_gen.py
fabrique_atelier/dummy/logger.py
fabrique_atelier/dummy/metric_collector.py
fabrique_atelier/dummy/pipeline_actors.py
fabrique_atelier/dummy/router.py
fabrique_atelier/dummy/store.py
fabrique_atelier/examples/__init__.py
fabrique_atelier/examples/easy_balloons/__init__.py
fabrique_atelier/examples/easy_balloons/pipeline.py
fabrique_atelier/examples/easy_balloons/dev/start_pipeline.ipynb
fabrique_atelier/examples/easy_balloons/dev/start_pipeline.py
fabrique_atelier/examples/fake_lightgbm/.gitignore
fabrique_atelier/examples/fake_lightgbm/README.md
fabrique_atelier/examples/fake_lightgbm/fake_lightgbm.py
fabrique_atelier/examples/fake_lightgbm/model.txt
fabrique_atelier/examples/fake_lightgbm/pipeline.py
fabrique_atelier/examples/fake_lightgbm/requirements.txt
fabrique_atelier/examples/fake_lightgbm/dev/__init__.py
fabrique_atelier/examples/fake_lightgbm/dev/decomposition.ipynb
fabrique_atelier/examples/fake_lightgbm/dev/start_ml_pipeline.ipynb
fabrique_atelier/examples/fake_lightgbm/dev/start_ml_pipeline.py
fabrique_atelier/examples/fake_lightgbm/dev/samples/mes0.json
fabrique_atelier/examples/fake_lightgbm/dev/samples/mes1.json
fabrique_atelier/examples/fake_lightgbm/dev/samples/mes10.json
fabrique_atelier/examples/fake_lightgbm/dev/samples/mes2.json
fabrique_atelier/examples/fake_lightgbm/dev/samples/mes3.json
fabrique_atelier/examples/fake_lightgbm/dev/samples/mes4.json
fabrique_atelier/examples/fake_lightgbm/dev/samples/mes5.json
fabrique_atelier/examples/fake_lightgbm/dev/samples/mes6.json
fabrique_atelier-5.0.9.dist-info/METADATA
fabrique_atelier-5.0.9.dist-info/WHEEL
fabrique_atelier-5.0.9.dist-info/top_level.txt
fabrique_atelier-5.0.9.dist-info/RECORD
