Metadata-Version: 2.1
Name: fabrique-atelier
Version: 5.0.9
Summary: Fabrique local environment
Home-page: http://www.fabrique.ai
Author: Sergey Kuzmin
Author-email: sergey.kuzmin@fabrique.ai
License: MIT
Keywords: ML pipeline
Platform: UNKNOWN
Classifier: Development Status :: 5 - Production/Stable
Classifier: License :: OSI Approved :: MIT License
Requires-Dist: msgpack (==0.6.2)
Requires-Dist: numpy
Requires-Dist: pytest
Requires-Dist: python-dateutil
Requires-Dist: pyyaml
